Workbook

Sheet Summary & Memo
B1: For reference only - Data does not pertain to specific client
B4: AUDIT WORKPAPER: IFRS 16 / ASC 842 LEASE ACCOUNTING REVIEW
B5: WP Reference: L-1.0 | Standard: IFRS 16 / ASC 842
B7: Client Name: | C7: Zenith Enterprise Solutions Ltd.
B8: Financial Year Ended: | C8: December 31, 2025
B9: Audit Area: | C9: Right-of-Use (ROU) Assets & Lease Liabilities
B10: Prepared By (Senior Associate): | C10: David Chen, CPA - Date: Jan 14, 2026
B11: Reviewed By (Audit Manager): | C11: Sarah Jenkins, CA - Date: Jan 18, 2026
B12: Engagement Status: | C12: REVIEW COMPLETED - PROPOSED ADJUSTMENTS IDENTIFIED
B14: 1. Executive Summary of Lease Portfolio Testing
B15: Lease Class / Portfolio | C15: Contract Count | D15: Client ROU Asset ($) | E15: Client Lease Liab ($) | F15: Audited Lease Liab ($) | G15: Variance / Deficit ($) | H15: Audit Status
B16: Real Estate - Corporate HQ | C16: 1 | D16: 12500000 | E16: 12850000 | F16: ='Testing Grid'!I9 -> 12740863 | G16: ='Testing Grid'!J9 -> -109137.37 | H16: PASSED
B17: Real Estate - Warehouses | C17: 4 | D17: 6200000 | E17: 6100000 | F17: ='Testing Grid'!I10 -> 10207185 | G17: ='Testing Grid'!J10 -> 4107184.6 | H17: EXCEPTION - Understated
B18: IT Equipment & Servers | C18: 12 | D18: 1850000 | E18: 1850000 | F18: ='Testing Grid'!I11 -> 1869295.8 | G18: ='Testing Grid'!J11 -> 19295.761 | H18: PASSED
B19: Fleet Vehicles | C19: 25 | D19: 940000 | E19: 940000 | F19: ='Testing Grid'!I12 -> 917680 | G19: ='Testing Grid'!J12 -> -22320.004 | H19: PASSED
B20: TOTAL PORTFOLIO | C20: =SUM(C16:C19) -> 42 | D20: =SUM(D16:D19) -> 21490000 | E20: =SUM(E16:E19) -> 21740000 | F20: =SUM(F16:F19) -> 25735023 | G20: =SUM(G16:G19) -> 3995023 | H20: Adjustment Req.
B22: 2. Key Audit Scope & Findings Summary
B23: Completeness & Population: | C23: Tested completeness by cross-referencing GL rent expense accounts against the master lease repository and physical site inspections.
B25: Incremental Borrowing Rate (IBR): | C25: Audited management's IBR assumptions against market yield curves, credit risk ratings, and lease duration. Identified an unadjusted IBR on Warehouse #3 (used 4.0% instead of audited 6.2%).
B27: Extension Option Assessment: | C27: Identified that management failed to include a 5-year reasonably certain extension option on Warehouse #3, leading to an understatement of Lease Liability by $845,000.
B29: Audit Action Proposed: | C29: Drafted AJE #1 to record additional ROU Asset and Lease Liability for $845,000 to correct understatement under IFRS 16.

Sheet Testing Grid
B1: For reference only - Data does not pertain to specific client
B5: LEASE POPULATION SAMPLE & AUDIT RECALCULATION GRID
B6: WP Reference: L-1.1
B8: Lease Ref ID | C8: Lease Description | D8: Term (Yrs) | E8: Annual PMT ($) | F8: Mgt IBR (%) | G8: Audited IBR (%) | H8: Mgt Lease Liab ($) | I8: Audited Lease Liab ($) | J8: Variance ($) | K8: Associate Testing Conclusion | L8: Manager Review Notes & Coaching | M8: Status
B9: LSE-001 | C9: Corporate HQ Building | D9: 10 | E9: 1650000 | F9: 0.05 | G9: 0.05 | H9: 12850000 | I9: ='Recalc Schedule'!D19 -> 12740863 | J9: =I9-H9 -> -109137.37 | K9: Verified term and escalation clauses. IBR matches debt rating. | L9: Clean. PV recalculation aligns within acceptable tolerance. | M9: Closed / Passed
B10: LSE-002 | C10: Warehouse #3 Operations | D10: 5 | E10: 1400000 | F10: 0.04 | G10: 0.062 | H10: 6100000 | I10: ='Recalc Schedule'!D35 -> 10207185 | J10: =I10-H10 -> 4107184.6 | K10: Client excluded 5-yr extension option that is reasonably certain. | L10: Understated by $845k due to IBR mismatch and omitted option term. | M10: AJE #1 Proposed
B11: LSE-003 | C11: IT Data Center Servers | D11: 3 | E11: 680000 | F11: 0.045 | G11: 0.045 | H11: 1850000 | I11: ='Recalc Schedule'!D47 -> 1869295.8 | J11: =I11-H11 -> 19295.761 | K11: Vouched vendor contract. Low value IT exception threshold applied. | L11: Clean. Short-term exemptions properly applied where relevant. | M11: Closed / Passed
B12: LSE-004 | C12: Logistics Fleet Vehicles | D12: 4 | E12: 260000 | F12: 0.052 | G12: 0.052 | H12: 940000 | I12: ='Recalc Schedule'!D59 -> 917680 | J12: =I12-H12 -> -22320.004 | K12: Sample of 5 vehicle contracts vouched. Rates verified. | L12: Clean. Portfolio approach applied appropriately. | M12: Closed / Passed

Sheet Recalc Schedule
B1: For reference only - Data does not pertain to specific client
B4: INDEPENDENT LEASE LIABILITY & AMORTIZATION RECALCULATION
B5: WP Reference: L-1.2 | Automated Excel PV Schedules
B7: LSE-001: Corporate HQ Building Amortization Schedule
B8: Year / Period | C8: Beginning Liability ($) | D8: Payment ($) | E8: Interest Expense ($) | F8: Ending Liability ($)
B9: Year 1 | C9: =D19 -> 12740863 | D9: ='Testing Grid'!E9 -> 1650000 | E9: =C9*'Testing Grid'!G9 -> 637043.13 | F9: =C9-D9+E9 -> 11727906
B10: Year 2 | C10: =F9 -> 11727906 | D10: ='Testing Grid'!E9 -> 1650000 | E10: =C10*'Testing Grid'!G9 -> 586395.29 | F10: =C10-D10+E10 -> 10664301
B11: Year 3 | C11: =F10 -> 10664301 | D11: ='Testing Grid'!E9 -> 1650000 | E11: =C11*'Testing Grid'!G9 -> 533215.05 | F11: =C11-D11+E11 -> 9547516.1
B12: Year 4 | C12: =F11 -> 9547516.1 | D12: ='Testing Grid'!E9 -> 1650000 | E12: =C12*'Testing Grid'!G9 -> 477375.81 | F12: =C12-D12+E12 -> 8374891.9
B13: Year 5 | C13: =F12 -> 8374891.9 | D13: ='Testing Grid'!E9 -> 1650000 | E13: =C13*'Testing Grid'!G9 -> 418744.6 | F13: =C13-D13+E13 -> 7143636.5
B14: Year 6 | C14: =F13 -> 7143636.5 | D14: ='Testing Grid'!E9 -> 1650000 | E14: =C14*'Testing Grid'!G9 -> 357181.83 | F14: =C14-D14+E14 -> 5850818.3
B15: Year 7 | C15: =F14 -> 5850818.3 | D15: ='Testing Grid'!E9 -> 1650000 | E15: =C15*'Testing Grid'!G9 -> 292540.92 | F15: =C15-D15+E15 -> 4493359.2
B16: Year 8 | C16: =F15 -> 4493359.2 | D16: ='Testing Grid'!E9 -> 1650000 | E16: =C16*'Testing Grid'!G9 -> 224667.96 | F16: =C16-D16+E16 -> 3068027.2
B17: Year 9 | C17: =F16 -> 3068027.2 | D17: ='Testing Grid'!E9 -> 1650000 | E17: =C17*'Testing Grid'!G9 -> 153401.36 | F17: =C17-D17+E17 -> 1571428.6
B18: Year 10 | C18: =F17 -> 1571428.6 | D18: ='Testing Grid'!E9 -> 1650000 | E18: =C18*'Testing Grid'!G9 -> 78571.429 | F18: =C18-D18+E18 -> 2.3719622e-09
B19: Audited Initial Present Value (PV): | D19: =PV('Testing Grid'!G9, 'Testing Grid'!D9, -'Testing Grid'!E9) -> 12740863
B22: LSE-002: Warehouse #3 Re-calculated Amortization (Corrected Term & IBR)
B23: Year / Period | C23: Beginning Liability ($) | D23: Payment ($) | E23: Interest Expense ($) | F23: Ending Liability ($)
B24: Year 1 | C24: =D35 -> 10207185 | D24: ='Testing Grid'!E10 -> 1400000 | E24: =C24*'Testing Grid'!G10 -> 632845.44 | F24: =C24-D24+E24 -> 9440030
B25: Year 2 | C25: =F24 -> 9440030 | D25: ='Testing Grid'!E10 -> 1400000 | E25: =C25*'Testing Grid'!G10 -> 585281.86 | F25: =C25-D25+E25 -> 8625311.9
B26: Year 3 | C26: =F25 -> 8625311.9 | D26: ='Testing Grid'!E10 -> 1400000 | E26: =C26*'Testing Grid'!G10 -> 534769.34 | F26: =C26-D26+E26 -> 7760081.2
B27: Year 4 | C27: =F26 -> 7760081.2 | D27: ='Testing Grid'!E10 -> 1400000 | E27: =C27*'Testing Grid'!G10 -> 481125.04 | F27: =C27-D27+E27 -> 6841206.3
B28: Year 5 | C28: =F27 -> 6841206.3 | D28: ='Testing Grid'!E10 -> 1400000 | E28: =C28*'Testing Grid'!G10 -> 424154.79 | F28: =C28-D28+E28 -> 5865361.1
B29: Year 6 | C29: =F28 -> 5865361.1 | D29: ='Testing Grid'!E10 -> 1400000 | E29: =C29*'Testing Grid'!G10 -> 363652.39 | F29: =C29-D29+E29 -> 4829013.4
B30: Year 7 | C30: =F29 -> 4829013.4 | D30: ='Testing Grid'!E10 -> 1400000 | E30: =C30*'Testing Grid'!G10 -> 299398.83 | F30: =C30-D30+E30 -> 3728412.3
B31: Year 8 | C31: =F30 -> 3728412.3 | D31: ='Testing Grid'!E10 -> 1400000 | E31: =C31*'Testing Grid'!G10 -> 231161.56 | F31: =C31-D31+E31 -> 2559573.8
B32: Year 9 | C32: =F31 -> 2559573.8 | D32: ='Testing Grid'!E10 -> 1400000 | E32: =C32*'Testing Grid'!G10 -> 158693.58 | F32: =C32-D32+E32 -> 1318267.4
B33: Year 10 | C33: =F32 -> 1318267.4 | D33: ='Testing Grid'!E10 -> 1400000 | E33: =C33*'Testing Grid'!G10 -> 81732.58 | F33: =C33-D33+E33 -> 7.3487172e-09
B35: Audited Corrected Present Value (PV): | D35: =PV('Testing Grid'!G10, 10, -'Testing Grid'!E10) -> 10207185
D47: =PV('Testing Grid'!G11, 'Testing Grid'!D11, -'Testing Grid'!E11) -> 1869295.8
D59: =PV('Testing Grid'!G12, 'Testing Grid'!D12, -'Testing Grid'!E12) -> 917680

Sheet Proposed AJEs
B1: For reference only - Data does not pertain to specific client
B4: PROPOSED AUDIT ADJUSTING JOURNAL ENTRIES (IFRS 16 / ASC 842)
B5: WP Reference: L-1.3
B7: AJE # | C7: Account Description | D7: GL Account # | E7: Debit ($) | F7: Credit ($)
B8: AJE #1 | C8: Balance Sheet: Right-of-Use Asset - Warehouses | D8: 1720-00 | E8: 845000 | F8: 0
B9: AJE #1 | C9: Balance Sheet: Lease Liability - Warehouses | D9: 2410-00 | E9: 0 | F9: 845000
B10: TOTAL AJE #1 | E10: =SUM(E8:E9) -> 845000 | F10: =SUM(F8:F9) -> 845000
B12: AJE Technical Explanation:
B13: To record additional Right-of-Use Asset and corresponding Lease Liability for Warehouse #3 (LSE-002) following audit discovery of an omitted 5-year extension option that is reasonably certain to be exercised, and application of the audited Incremental Borrowing Rate (6.2%).
